santo/__init__.py
santo/data.py
santo/model.py
santo/utils.py
SANTO-0.0.3.dist-info/LICENSE
SANTO-0.0.3.dist-info/METADATA
SANTO-0.0.3.dist-info/WHEEL
SANTO-0.0.3.dist-info/top_level.txt
SANTO-0.0.3.dist-info/RECORD
